invenio_query_parser/__init__.py
invenio_query_parser/_compat.py
invenio_query_parser/ast.py
invenio_query_parser/parser.py
invenio_query_parser/utils.py
invenio_query_parser/version.py
invenio_query_parser/visitor.py
invenio_query_parser/contrib/__init__.py
invenio_query_parser/contrib/elasticsearch/__init__.py
invenio_query_parser/contrib/elasticsearch/walkers/__init__.py
invenio_query_parser/contrib/elasticsearch/walkers/dsl.py
invenio_query_parser/contrib/spires/__init__.py
invenio_query_parser/contrib/spires/ast.py
invenio_query_parser/contrib/spires/config.py
invenio_query_parser/contrib/spires/converter.py
invenio_query_parser/contrib/spires/parser.py
invenio_query_parser/contrib/spires/walkers/__init__.py
invenio_query_parser/contrib/spires/walkers/printer.py
invenio_query_parser/contrib/spires/walkers/pypeg_to_ast.py
invenio_query_parser/contrib/spires/walkers/spires_to_invenio.py
invenio_query_parser/contrib/spires/walkers/tree_printer.py
invenio_query_parser/walkers/__init__.py
invenio_query_parser/walkers/match_unit.py
invenio_query_parser/walkers/printer.py
invenio_query_parser/walkers/pypeg_to_ast.py
invenio_query_parser/walkers/repr_printer.py
invenio_query_parser-0.6.0.dist-info/top_level.txt
invenio_query_parser-0.6.0.dist-info/METADATA
invenio_query_parser-0.6.0.dist-info/DESCRIPTION.rst
invenio_query_parser-0.6.0.dist-info/metadata.json
invenio_query_parser-0.6.0.dist-info/WHEEL
invenio_query_parser-0.6.0.dist-info/RECORD
