Metadata-Version: 2.0
Name: invenio-query-parser
Version: 0.6.0
Summary: Search query parser supporting Invenio and SPIRES search syntax.
Home-page: https://github.com/inveniosoftware/invenio-query-parser
Author: Invenio collaboration
Author-email: info@invenio-software.org
License: GPLv2
Platform: UNKNOWN
Classifier: Programming Language :: Python :: 2
Classifier: Programming Language :: Python :: 2.7
Classifier: Programming Language :: Python :: 3
Classifier: Programming Language :: Python :: 3.3
Classifier: Programming Language :: Python :: 3.4
Classifier: Programming Language :: Python :: 3.5
Classifier: Development Status :: 5 - Production/Stable
Classifier: Intended Audience :: Developers
Classifier: License :: OSI Approved :: GNU General Public License v2 or later (GPLv2+)
Classifier: Operating System :: OS Independent
Classifier: Topic :: Utilities
Requires-Dist: pypeg2 (>=2.15.2)
Requires-Dist: ordereddict (>=1.1)
Requires-Dist: six (>=1.10.0)
Provides-Extra: docs
Requires-Dist: sphinx-rtd-theme (>=0.1.9); extra == 'docs'
Provides-Extra: elasticsearch
Requires-Dist: elasticsearch-dsl (>=2.0.0); extra == 'elasticsearch'
Provides-Extra: tests
Requires-Dist: check-manifest (>=0.25); extra == 'tests'
Requires-Dist: coverage (>=4.0.0); extra == 'tests'
Requires-Dist: isort (>=4.2.2); extra == 'tests'
Requires-Dist: pydocstyle (>=1.0.0); extra == 'tests'
Requires-Dist: pytest-cache (>=1.0); extra == 'tests'
Requires-Dist: pytest-cov (>=2.1.0); extra == 'tests'
Requires-Dist: pytest-pep8 (>=1.0.6); extra == 'tests'
Requires-Dist: pytest-runner (>=2.7.0); extra == 'tests'
Requires-Dist: pytest (>=2.8.0); extra == 'tests'
